[
    {
        "title": "Grounding Earth Connection",
        "duration": 1202,
        "category": "Earth Month",
        "audioFileFolder": "special_event/spring_reset",
        "audioFileName": "Grounding_Earth_Connection_Aria.mp3",
        "thumbnailUrl": "Grounding_Earth_Connection",
        "instructor": "Aria",
        "premium": "n",
        "ElevenLabs_name": "Natasha - Gentle Meditation",
        "description": "A deeply grounding practice that connects you with Earth's stabilizing energy. Perfect for those feeling scattered or unrooted in their daily lives.",
        "principles": "earth visualization, root chakra focus, grounding techniques",
        "words": 500,
        "text_file_name": "Grounding_Earth_Connection.txt",
        "gender": "Female",
        "order": 44
    },
    {
        "title": "Forest Bathing Rest",
        "duration": 1200,
        "category": "Earth Month",
        "audioFileFolder": "special_event/spring_reset",
        "audioFileName": "Forest_Bathing_Rest_Drew.mp3",
        "thumbnailUrl": "Forest_Bathing_Rest",
        "instructor": "Drew",
        "premium": "n",
        "ElevenLabs_name": "Joseph - Guided Meditation",
        "description": "Inspired by the Japanese practice of Shinrin-Yoku, this session brings the calming benefits of forest immersion to your relaxation practice.",
        "principles": "nature sounds integration, forest visualization, phytoncide awareness",
        "words": 500,
        "text_file_name": "Forest_Bathing_Rest.txt",
        "gender": "Male",
        "order": 45
    },
    {
        "title": "Mountain Stillness",
        "duration": 1244,
        "category": "Earth Month",
        "audioFileFolder": "special_event/spring_reset",
        "audioFileName": "Mountain_Stillness_James.mp3",
        "thumbnailUrl": "Mountain_Stillness",
        "instructor": "James",
        "premium": "n",
        "ElevenLabs_name": "Jameson - Guided Meditation",
        "description": "Embody the unwavering presence and stability of mountains in this deep relaxation practice. Builds inner strength while promoting complete rest.",
        "principles": "mountain visualization, steadiness cultivation, present awareness",
        "words": 500,
        "text_file_name": "Mountain_Stillness.txt",
        "gender": "Male",
        "order": 46
    },
    {
        "title": "Ocean Rhythms",
        "duration": 1129,
        "category": "Earth Month",
        "audioFileFolder": "special_event/spring_reset",
        "audioFileName": "Ocean_Rhythms_Brittney.mp3",
        "thumbnailUrl": "Ocean_Rhythms",
        "instructor": "Brittney",
        "premium": "n",
        "ElevenLabs_name": "Brittney",
        "description": "Synchronize with the natural ebb and flow of ocean tides to regulate your nervous system and promote deeper sleep patterns.",
        "principles": "wave breathing, tidal rhythm awareness, fluid body scanning",
        "words": 500,
        "text_file_name": "Ocean_Rhythms.txt",
        "gender": "Female",
        "order": 47
    },
    {
        "title": "Seed to Sprout",
        "duration": 1353,
        "category": "Earth Month",
        "audioFileFolder": "special_event/spring_reset",
        "audioFileName": "Seed_to_Sprout_Aria.mp3",
        "thumbnailUrl": "Seed_to_Sprout",
        "instructor": "Aria",
        "premium": "n",
        "ElevenLabs_name": "Natasha - Gentle Meditation",
        "description": "A regenerative practice modeling the wisdom of seeds - rest before growth. Perfect for those seeking renewal while honoring necessary dormancy.",
        "principles": "seed wisdom, patience practice, potential nurturing",
        "words": 500,
        "text_file_name": "Seed_to_Sprout.txt",
        "gender": "Female",
        "order": 48
    },
    {
        "title": "Earth Element Balance",
        "duration": 1369,
        "category": "Earth Month",
        "audioFileFolder": "special_event/spring_reset",
        "audioFileName": "Earth_Element_Balance_Drew.mp3",
        "thumbnailUrl": "Earth_Element_Balance",
        "instructor": "Drew",
        "premium": "n",
        "ElevenLabs_name": "Joseph - Guided Meditation",
        "description": "Restore elemental balance through connection with earth energy. Particularly helpful for those feeling ungrounded or overly mental.",
        "principles": "elemental awareness, body-earth connection, stability cultivation",
        "words": 500,
        "text_file_name": "Earth_Element_Balance.txt",
        "gender": "Male",
        "order": 49
    },
    {
        "title": "Starlight Perspective",
        "duration": 1198,
        "category": "Earth Month",
        "audioFileFolder": "special_event/spring_reset",
        "audioFileName": "Starlight_Perspective_Brittney.mp3",
        "thumbnailUrl": "Starlight_Perspective",
        "instructor": "Brittney",
        "premium": "n",
        "ElevenLabs_name": "Brittney",
        "description": "Gain cosmic perspective while remaining grounded through this practice connecting Earth's solidity with the vast perspective of starlight.",
        "principles": "cosmic perspective, grounding paradox, earth-sky integration",
        "words": 500,
        "text_file_name": "Starlight_Perspective.txt",
        "gender": "Female",
        "order": 50
    },
    {
        "title": "Garden of Rest",
        "duration": 1229,
        "category": "Earth Month",
        "audioFileFolder": "special_event/spring_reset",
        "audioFileName": "Garden_of_Rest_James.mp3",
        "thumbnailUrl": "Garden_of_Rest",
        "instructor": "James",
        "premium": "n",
        "ElevenLabs_name": "Jameson - Guided Meditation",
        "description": "A shorter practice visualizing the mind as a garden where restfulness can bloom. Perfect for creating fertile conditions for growth.",
        "principles": "garden visualization, mental cultivation, fertile rest",
        "words": 500,
        "text_file_name": "Garden_of_Rest.txt",
        "gender": "Male",
        "order": 51
    },
    {
        "title": "Ancient Tree Wisdom",
        "duration": 1312,
        "category": "Earth Month",
        "audioFileFolder": "special_event/spring_reset",
        "audioFileName": "Ancient_Tree_Wisdom_Aria.mp3",
        "thumbnailUrl": "Ancient_Tree_Wisdom",
        "instructor": "Aria",
        "premium": "n",
        "ElevenLabs_name": "Natasha - Gentle Meditation",
        "description": "Connect with the deep rooted wisdom of ancient trees in this practice emphasizing patience, resilience and the power of slow growth.",
        "principles": "tree visualization, rootedness, seasonal wisdom",
        "words": 500,
        "text_file_name": "Ancient_Tree_Wisdom.txt",
        "gender": "Female",
        "order": 52
    },
    {
        "title": "Earth Heartbeat",
        "duration": 1341,
        "category": "Earth Month",
        "audioFileFolder": "special_event/spring_reset",
        "audioFileName": "Earth_Heartbeat_Brittney.mp3",
        "thumbnailUrl": "Earth_Heartbeat",
        "instructor": "Brittney",
        "premium": "n",
        "ElevenLabs_name": "Brittney",
        "description": "Synchronize with Earth's natural rhythms and cycles in this practice that helps regulate your own internal body clock and stress response.",
        "principles": "rhythm entrainment, earth pulse connection, circadian alignment",
        "words": 500,
        "text_file_name": "Earth_Heartbeat.txt",
        "gender": "Female",
        "order": 53
    },
    {
        "title": "Spring Awakening",
        "duration": 1379,
        "category": "Spring Reset",
        "audioFileFolder": "special_event/spring_reset",
        "audioFileName": "Spring_Awakening_Aria.mp3",
        "thumbnailUrl": "Spring_Awakening",
        "instructor": "Aria",
        "premium": "n",
        "ElevenLabs_name": "Natasha - Gentle Meditation",
        "description": "A gentle practice to awaken your body's natural renewal rhythms. This session helps transition from winter stagnation to spring's natural energy while maintaining deep restfulness.",
        "principles": "progressive relaxation, breath awareness, renewal intention",
        "words": 500,
        "text_file_name": "Spring_Awakening.txt",
        "gender": "Female",
        "order": 54
    },
    {
        "title": "Seasonal Transition",
        "duration": 1232,
        "category": "Spring Reset",
        "audioFileFolder": "special_event/spring_reset",
        "audioFileName": "Seasonal_Transition_Drew.mp3",
        "thumbnailUrl": "Seasonal_Transition",
        "instructor": "Drew",
        "premium": "n",
        "ElevenLabs_name": "Joseph - Guided Meditation",
        "description": "Designed to help your body adjust to changing daylight patterns and seasonal shifts. This practice supports your circadian rhythm reset while guiding you into profound relaxation.",
        "principles": "body scanning, light visualization, circadian awareness",
        "words": 500,
        "text_file_name": "Seasonal_Transition.txt",
        "gender": "Male",
        "order": 55
    },
    {
        "title": "Refresh & Renew",
        "duration": 1454,
        "category": "Spring Reset",
        "audioFileFolder": "special_event/spring_reset",
        "audioFileName": "Refresh_Renew_Brittney.mp3",
        "thumbnailUrl": "Refresh_Renew",
        "instructor": "Brittney",
        "premium": "n",
        "ElevenLabs_name": "Brittney",
        "description": "A revitalizing practice to clear winter's heaviness from both mind and body. This session combines gentle energy activation with deep relaxation techniques.",
        "principles": "energy activation, tension-release, renewal sankalpas",
        "words": 500,
        "text_file_name": "Refresh_Renew.txt",
        "gender": "Female",
        "order": 56
    },
    {
        "title": "New Growth Rest",
        "duration": 1240,
        "category": "Spring Reset",
        "audioFileFolder": "special_event/spring_reset",
        "audioFileName": "New_Growth_Rest_James.mp3",
        "thumbnailUrl": "New_Growth_Rest",
        "instructor": "James",
        "premium": "n",
        "ElevenLabs_name": "Jameson - Guided Meditation",
        "description": "Inspired by nature's renewal cycle, this practice nurtures the conditions for new growth in your life while maintaining deep restfulness.",
        "principles": "growth visualization, seed sankalpas, body rotation awareness",
        "words": 500,
        "text_file_name": "New_Growth_Rest.txt",
        "gender": "Male",
        "order": 57
    },
    {
        "title": "Clearing Space",
        "duration": 1329,
        "category": "Spring Reset",
        "audioFileFolder": "special_event/spring_reset",
        "audioFileName": "Clearing_Space_Aria.mp3",
        "thumbnailUrl": "Clearing_Space",
        "instructor": "Aria",
        "premium": "n",
        "ElevenLabs_name": "Natasha - Gentle Meditation",
        "description": "A purifying practice focused on releasing accumulated tension and creating space for fresh energy and clearer thinking.",
        "principles": "mental decluttering, breath cleansing, witness consciousness",
        "words": 500,
        "text_file_name": "Clearing_Space.txt",
        "gender": "Female",
        "order": 58
    },
    {
        "title": "Dawn Renewal",
        "duration": 1239,
        "category": "Spring Reset",
        "audioFileFolder": "special_event/spring_reset",
        "audioFileName": "Dawn_Renewal_Drew.mp3",
        "thumbnailUrl": "Dawn_Renewal",
        "instructor": "Drew",
        "premium": "n",
        "ElevenLabs_name": "Joseph - Guided Meditation",
        "description": "A shorter practice designed to reset your energy with the rising sun. Perfect for morning practice to align with spring's earlier dawns.",
        "principles": "gentle awakening, light visualization, intention setting",
        "words": 500,
        "text_file_name": "Dawn_Renewal.txt",
        "gender": "Male",
        "order": 59
    },
    {
        "title": "Balanced Transition",
        "duration": 1247,
        "category": "Spring Reset",
        "audioFileFolder": "special_event/spring_reset",
        "audioFileName": "Balanced_Transition_James.mp3",
        "thumbnailUrl": "Balanced_Transition",
        "instructor": "James",
        "premium": "n",
        "ElevenLabs_name": "Jameson - Guided Meditation",
        "description": "Supports balance during seasonal change by stabilizing energy and promoting adaptability. Excellent for those sensitive to seasonal transitions.",
        "principles": "equilibrium techniques, grounding visualization, adaptability focus",
        "words": 500,
        "text_file_name": "Balanced_Transition.txt",
        "gender": "Male",
        "order": 60
    }
]
